deletion_side_effects/__init__.py
deletion_side_effects/apps.py
deletion_side_effects/deletion_side_effects.py
deletion_side_effects/version.py
deletion_side_effects/tests/__init__.py
deletion_side_effects/tests/test_deletion_side_effects.py
django_deletion_side_effects-2.1.0.dist-info/LICENSE
django_deletion_side_effects-2.1.0.dist-info/METADATA
django_deletion_side_effects-2.1.0.dist-info/WHEEL
django_deletion_side_effects-2.1.0.dist-info/top_level.txt
django_deletion_side_effects-2.1.0.dist-info/RECORD
