Metadata-Version: 2.1
Name: django-deletion-side-effects
Version: 2.1.0
Summary: Provides the ability to retrieve the side effects of deleting an object in Django
Home-page: https://github.com/ambitioninc/django-deletion-side-effects
Author: Wes Kendall
Author-email: opensource@ambition.com
License: MIT
Classifier: Programming Language :: Python
Classifier: Programming Language :: Python :: 3.7
Classifier: Programming Language :: Python :: 3.8
Classifier: Programming Language :: Python :: 3.9
Classifier: Intended Audience :: Developers
Classifier: License :: OSI Approved :: MIT License
Classifier: Operating System :: OS Independent
Classifier: Framework :: Django :: 3.2
Classifier: Framework :: Django :: 4.0
Classifier: Framework :: Django :: 4.1
Classifier: Framework :: Django :: 4.2
License-File: LICENSE
Requires-Dist: Django (<5.0,>=3.2)
